[
  {
    "_id": "58c03ac18060196ca1b51d51",
    "movie": "5bc6a228b703d1d79075c26f",
    "cinema": "58c03ac18060197ca0b52c51",
    "sessionDateTime": [
      "2017-03-08T17:09:21.627Z",
      "2017-03-08T17:10:21.627Z",
      "2018-03-08T17:09:21.627Z"
    ],
    "ticketLink": "https://www.eventcinemas.com.au/Orders/Tickets#sessionId=9032724",
    "created": "2017-03-08T17:09:21.627Z",
    "Updated": "2017-03-08T17:09:21.627Z"
  },

  {
    "_id": "56c03ac18060297ca0b42c53",
    "movie": "5bc6a228b703d1d79175c26f",
    "cinema": "56c03ac18060297ca0b52c53",
    "sessionDateTime": [
      "2016-03-08T17:09:21.627Z",
      "2018-03-08T17:10:21.627Z",
      "2017-03-08T17:09:21.627Z"
    ],
    "ticketLink": "https://someticket.site",
    "created": "2017-03-08T17:09:21.627Z",
    "Updated": "2017-03-08T17:09:21.627Z"
  },
  {
    "_id": "56c03ac18060297ca0b52c50",
    "movie": "5bc6a228b703d1d79075c26f",
    "cinema": "56c03ac18060297ca0b52c52",
    "sessionDateTime": [
      "2016-03-08T17:09:21.627Z",
      "2018-03-08T17:10:21.627Z",
      "2017-03-08T17:09:21.627Z"
    ],
    "ticketLink": "https://someticket.site",
    "created": "2017-03-08T17:09:21.627Z",
    "Updated": "2017-03-08T17:09:21.627Z"
  },

  {
    "_id": "58c03ac18060196ca0b51d51",
    "movie": "5bc6a228b703d1d79175c26f",
    "cinema": "56c03ac18060297ca0b52c52",
    "sessionDateTime": [
      "2017-10-08T17:09:21.627Z",
      "2017-10-08T17:10:21.627Z",
      "2018-10-08T17:09:21.627Z"
    ],
    "ticketLink": "https://www.eventcinemas.com.au/Orders/Tickets#sessionId=9032724",
    "created": "2017-03-08T17:09:21.627Z",
    "Updated": "2017-03-08T17:09:21.627Z"
  },

  {
    "_id": "56c03ac18060296ca0b52c53",
    "movie": "5bc6a228b703d1d79175c26f",
    "cinema": "58c03ac18060197ca0b52c51",
    "sessionDateTime": [
      "2016-10-08T17:09:21.627Z",
      "2018-10-08T17:10:21.627Z",
      "2017-10-08T17:09:21.627Z"
    ],
    "ticketLink": "https://someticket.site",
    "created": "2017-03-08T17:09:21.627Z",
    "Updated": "2017-03-08T17:09:21.627Z"
  },
  {
    "_id": "58c03ac18160196ca0b51d51",
    "movie": "5bc6f8ffe6977f003ebcaab5",
    "cinema": "58c03ac18060197ca0b52d50",
    "sessionDateTime": [
      "2017-12-08T17:09:21.627Z",
      "2017-12-08T17:10:21.627Z",
      "2018-12-12T17:09:21.627Z"
    ],
    "ticketLink": "https://www.village/Orders/Tickets#sessionId=9032724",
    "created": "2017-03-08T17:09:21.627Z",
    "Updated": "2017-03-08T17:09:21.627Z"
  },

  {
    "_id": "58c03ac18160196ca5b51e51",
    "movie": "5bd136f8c7b9b03de4110c14",
    "cinema": "58c03ac18060197ca0b52d50",
    "sessionDateTime": [
      "2018-12-08T17:09:21.627Z",
      "2018-12-08T17:10:21.627Z",
      "2018-12-12T17:09:21.627Z"
    ],
    "ticketLink": "https://www.village/Orders/Tickets#sessionId=9032724",
    "created": "2018-10-25T03:22:32.167Z",
    "Updated": "2018-10-25T03:22:32.167Z"
  }
]
